brioa_port/__init__.py
brioa_port/exceptions.py
brioa_port/log_keeper.py
brioa_port/schedule_parser.py
brioa_port/scripts/__init__.py
brioa_port/scripts/brioa_schedule.py
brioa_port/scripts/brioa_timelapse_creator.py
brioa_port/scripts/brioa_webcam_downloader.py
brioa_port/timelapse_frame_processor.py
brioa_port/util/__init__.py
brioa_port/util/args.py
brioa_port/util/database.py
brioa_port/util/datetime.py
brioa_port/util/entry.py
brioa_port/util/request.py
brioa_port/webcam_downloader.py
brioa_port-0.1.0.dist-info/entry_points.txt
brioa_port-0.1.0.dist-info/WHEEL
brioa_port-0.1.0.dist-info/METADATA
brioa_port-0.1.0.dist-info/RECORD
